zyjared_cli/__init__.py
zyjared_cli/cli/__init__.py
zyjared_cli/cli/app.py
zyjared_cli/cli/clean.py
zyjared_cli/cli/config.py
zyjared_cli/cli/push.py
zyjared_cli/cli/venv/__init__.py
zyjared_cli/cli/venv/_app.py
zyjared_cli/cli/venv/activate.py
zyjared_cli/cli/venv/add.py
zyjared_cli/cli/venv/clean.py
zyjared_cli/cli/venv/info.py
zyjared_cli/cli/venv/ls.py
zyjared_cli/cli/venv/remove.py
zyjared_cli/cli/version/__init__.py
zyjared_cli/cli/version/version.py
zyjared_cli/helpers/__init__.py
zyjared_cli/helpers/command.py
zyjared_cli/helpers/config.py
zyjared_cli/helpers/log.py
zyjared_cli/helpers/version.py
zyjared_cli/main.py
zyjared_cli/utils/time_unit.py
zyjared_cli-0.1.17.dist-info/LICENSE
zyjared_cli-0.1.17.dist-info/METADATA
zyjared_cli-0.1.17.dist-info/WHEEL
zyjared_cli-0.1.17.dist-info/entry_points.txt
zyjared_cli-0.1.17.dist-info/RECORD
